{
  "report_type": "detailed",
  "generated_at": 1762372170.4420104,
  "timestamp": "2025-11-06T03:49:30.442010",
  "modules": {
    "module_1": {
      "module_name": "module_1",
      "total_tests": 15,
      "passed_tests": 3,
      "failed_tests": 6,
      "skipped_tests": 2,
      "error_tests": 4,
      "warning_tests": 0,
      "success_rate": 20.0,
      "last_update": 1762372167.348504,
      "average_duration": 2.0897025868953905,
      "status": "error"
    },
    "module_2": {
      "module_name": "module_2",
      "total_tests": 15,
      "passed_tests": 5,
      "failed_tests": 3,
      "skipped_tests": 0,
      "error_tests": 7,
      "warning_tests": 0,
      "success_rate": 33.33333333333333,
      "last_update": 1762372169.087011,
      "average_duration": 2.8542150790100766,
      "status": "error"
    },
    "module_3": {
      "module_name": "module_3",
      "total_tests": 15,
      "passed_tests": 4,
      "failed_tests": 5,
      "skipped_tests": 6,
      "error_tests": 0,
      "warning_tests": 0,
      "success_rate": 26.666666666666668,
      "last_update": 1762372170.425946,
      "average_duration": 2.3593815731390384,
      "status": "failed"
    }
  },
  "test_results": {
    "module_1_test_1": {
      "test_id": "module_1_test_1",
      "test_name": "测试用例 1",
      "module_name": "module_1",
      "status": "skipped",
      "duration": 3.1428861095277427,
      "timestamp": 1762372165.7615073,
      "message": "测试失败",
      "error_details": "",
      "metadata": {}
    },
    "module_1_test_2": {
      "test_id": "module_1_test_2",
      "test_name": "测试用例 2",
      "module_name": "module_1",
      "status": "failed",
      "duration": 0.5996926125103793,
      "timestamp": 1762372165.8158545,
      "message": "测试失败",
      "error_details": "",
      "metadata": {}
    },
    "module_1_test_3": {
      "test_id": "module_1_test_3",
      "test_name": "测试用例 3",
      "module_name": "module_1",
      "status": "error",
      "duration": 2.1041731921419293,
      "timestamp": 1762372165.9372718,
      "message": "测试失败",
      "error_details": "",
      "metadata": {}
    },
    "module_1_test_4": {
      "test_id": "module_1_test_4",
      "test_name": "测试用例 4",
      "module_name": "module_1",
      "status": "passed",
      "duration": 2.7475294176749676,
      "timestamp": 1762372166.055282,
      "message": "测试执行完成",
      "error_details": "",
      "metadata": {}
    },
    "module_1_test_5": {
      "test_id": "module_1_test_5",
      "test_name": "测试用例 5",
      "module_name": "module_1",
      "status": "failed",
      "duration": 0.8877151280492928,
      "timestamp": 1762372166.1115997,
      "message": "测试失败",
      "error_details": "",
      "metadata": {}
    },
    "module_1_test_6": {
      "test_id": "module_1_test_6",
      "test_name": "测试用例 6",
      "module_name": "module_1",
      "status": "failed",
      "duration": 0.10873904680939449,
      "timestamp": 1762372166.2355654,
      "message": "测试失败",
      "error_details": "",
      "metadata": {}
    },
    "module_1_test_7": {
      "test_id": "module_1_test_7",
      "test_name": "测试用例 7",
      "module_name": "module_1",
      "status": "error",
      "duration": 2.114162392044946,
      "timestamp": 1762372166.3599255,
      "message": "测试失败",
      "error_details": "",
      "metadata": {}
    },
    "module_1_test_8": {
      "test_id": "module_1_test_8",
      "test_name": "测试用例 8",
      "module_name": "module_1",
      "status": "passed",
      "duration": 1.1288568685710492,
      "timestamp": 1762372166.4784353,
      "message": "测试执行完成",
      "error_details": "",
      "metadata": {}
    },
    "module_1_test_9": {
      "test_id": "module_1_test_9",
      "test_name": "测试用例 9",
      "module_name": "module_1",
      "status": "error",
      "duration": 2.0525553756128208,
      "timestamp": 1762372166.5354438,
      "message": "测试失败",
      "error_details": "",
      "metadata": {}
    },
    "module_1_test_10": {
      "test_id": "module_1_test_10",
      "test_name": "测试用例 10",
      "module_name": "module_1",
      "status": "skipped",
      "duration": 4.205373620996613,
      "timestamp": 1762372166.6626341,
      "message": "测试失败",
      "error_details": "",
      "metadata": {}
    },
    "module_1_test_11": {
      "test_id": "module_1_test_11",
      "test_name": "测试用例 11",
      "module_name": "module_1",
      "status": "error",
      "duration": 4.113992857107769,
      "timestamp": 1762372166.721729,
      "message": "测试失败",
      "error_details": "",
      "metadata": {}
    },
    "module_1_test_12": {
      "test_id": "module_1_test_12",
      "test_name": "测试用例 12",
      "module_name": "module_1",
      "status": "failed",
      "duration": 2.3919427159242317,
      "timestamp": 1762372166.8457892,
      "message": "测试失败",
      "error_details": "",
      "metadata": {}
    },
    "module_1_test_13": {
      "test_id": "module_1_test_13",
      "test_name": "测试用例 13",
      "module_name": "module_1",
      "status": "failed",
      "duration": 4.584292944320565,
      "timestamp": 1762372166.9812033,
      "message": "测试失败",
      "error_details": "",
      "metadata": {}
    },
    "module_1_test_14": {
      "test_id": "module_1_test_14",
      "test_name": "测试用例 14",
      "module_name": "module_1",
      "status": "failed",
      "duration": 0.38794979384356787,
      "timestamp": 1762372167.1197312,
      "message": "测试失败",
      "error_details": "",
      "metadata": {}
    },
    "module_1_test_15": {
      "test_id": "module_1_test_15",
      "test_name": "测试用例 15",
      "module_name": "module_1",
      "status": "passed",
      "duration": 0.7756767282955879,
      "timestamp": 1762372167.2828982,
      "message": "测试执行完成",
      "error_details": "",
      "metadata": {}
    },
    "module_2_test_1": {
      "test_id": "module_2_test_1",
      "test_name": "测试用例 1",
      "module_name": "module_2",
      "status": "failed",
      "duration": 4.884681606937248,
      "timestamp": 1762372167.348516,
      "message": "测试失败",
      "error_details": "",
      "metadata": {}
    },
    "module_2_test_2": {
      "test_id": "module_2_test_2",
      "test_name": "测试用例 2",
      "module_name": "module_2",
      "status": "error",
      "duration": 1.6854614357567281,
      "timestamp": 1762372167.497142,
      "message": "测试失败",
      "error_details": "",
      "metadata": {}
    },
    "module_2_test_3": {
      "test_id": "module_2_test_3",
      "test_name": "测试用例 3",
      "module_name": "module_2",
      "status": "error",
      "duration": 3.7033110126242477,
      "timestamp": 1762372167.6653788,
      "message": "测试失败",
      "error_details": "",
      "metadata": {}
    },
    "module_2_test_4": {
      "test_id": "module_2_test_4",
      "test_name": "测试用例 4",
      "module_name": "module_2",
      "status": "error",
      "duration": 3.8907449933581546,
      "timestamp": 1762372167.8208992,
      "message": "测试失败",
      "error_details": "",
      "metadata": {}
    },
    "module_2_test_5": {
      "test_id": "module_2_test_5",
      "test_name": "测试用例 5",
      "module_name": "module_2",
      "status": "passed",
      "duration": 0.48014285646753097,
      "timestamp": 1762372167.9779096,
      "message": "测试执行完成",
      "error_details": "",
      "metadata": {}
    },
    "module_2_test_6": {
      "test_id": "module_2_test_6",
      "test_name": "测试用例 6",
      "module_name": "module_2",
      "status": "passed",
      "duration": 0.42340164516086487,
      "timestamp": 1762372168.0421317,
      "message": "测试执行完成",
      "error_details": "",
      "metadata": {}
    },
    "module_2_test_7": {
      "test_id": "module_2_test_7",
      "test_name": "测试用例 7",
      "module_name": "module_2",
      "status": "error",
      "duration": 1.6327154852275776,
      "timestamp": 1762372168.108116,
      "message": "测试失败",
      "error_details": "",
      "metadata": {}
    },
    "module_2_test_8": {
      "test_id": "module_2_test_8",
      "test_name": "测试用例 8",
      "module_name": "module_2",
      "status": "passed",
      "duration": 3.6071075123670044,
      "timestamp": 1762372168.2454085,
      "message": "测试执行完成",
      "error_details": "",
      "metadata": {}
    },
    "module_2_test_9": {
      "test_id": "module_2_test_9",
      "test_name": "测试用例 9",
      "module_name": "module_2",
      "status": "error",
      "duration": 4.367238848937575,
      "timestamp": 1762372168.3065019,
      "message": "测试失败",
      "error_details": "",
      "metadata": {}
    },
    "module_2_test_10": {
      "test_id": "module_2_test_10",
      "test_name": "测试用例 10",
      "module_name": "module_2",
      "status": "failed",
      "duration": 1.885444320620022,
      "timestamp": 1762372168.432884,
      "message": "测试失败",
      "error_details": "",
      "metadata": {}
    },
    "module_2_test_11": {
      "test_id": "module_2_test_11",
      "test_name": "测试用例 11",
      "module_name": "module_2",
      "status": "passed",
      "duration": 3.178933806647431,
      "timestamp": 1762372168.5743496,
      "message": "测试执行完成",
      "error_details": "",
      "metadata": {}
    },
    "module_2_test_12": {
      "test_id": "module_2_test_12",
      "test_name": "测试用例 12",
      "module_name": "module_2",
      "status": "error",
      "duration": 4.577606684774431,
      "timestamp": 1762372168.6354334,
      "message": "测试失败",
      "error_details": "",
      "metadata": {}
    },
    "module_2_test_13": {
      "test_id": "module_2_test_13",
      "test_name": "测试用例 13",
      "module_name": "module_2",
      "status": "error",
      "duration": 3.233809341471423,
      "timestamp": 1762372168.7569575,
      "message": "测试失败",
      "error_details": "",
      "metadata": {}
    },
    "module_2_test_14": {
      "test_id": "module_2_test_14",
      "test_name": "测试用例 14",
      "module_name": "module_2",
      "status": "passed",
      "duration": 3.8646310119946725,
      "timestamp": 1762372168.886421,
      "message": "测试执行完成",
      "error_details": "",
      "metadata": {}
    },
    "module_2_test_15": {
      "test_id": "module_2_test_15",
      "test_name": "测试用例 15",
      "module_name": "module_2",
      "status": "failed",
      "duration": 1.3979956228062422,
      "timestamp": 1762372168.9552422,
      "message": "测试失败",
      "error_details": "",
      "metadata": {}
    },
    "module_3_test_1": {
      "test_id": "module_3_test_1",
      "test_name": "测试用例 1",
      "module_name": "module_3",
      "status": "failed",
      "duration": 2.460097279230018,
      "timestamp": 1762372169.087026,
      "message": "测试失败",
      "error_details": "",
      "metadata": {}
    },
    "module_3_test_2": {
      "test_id": "module_3_test_2",
      "test_name": "测试用例 2",
      "module_name": "module_3",
      "status": "passed",
      "duration": 1.2842654181519506,
      "timestamp": 1762372169.225389,
      "message": "测试执行完成",
      "error_details": "",
      "metadata": {}
    },
    "module_3_test_3": {
      "test_id": "module_3_test_3",
      "test_name": "测试用例 3",
      "module_name": "module_3",
      "status": "skipped",
      "duration": 2.5357744121947663,
      "timestamp": 1762372169.2937288,
      "message": "测试失败",
      "error_details": "",
      "metadata": {}
    },
    "module_3_test_4": {
      "test_id": "module_3_test_4",
      "test_name": "测试用例 4",
      "module_name": "module_3",
      "status": "failed",
      "duration": 3.347654049102881,
      "timestamp": 1762372169.3593583,
      "message": "测试失败",
      "error_details": "",
      "metadata": {}
    },
    "module_3_test_5": {
      "test_id": "module_3_test_5",
      "test_name": "测试用例 5",
      "module_name": "module_3",
      "status": "skipped",
      "duration": 2.955700635534042,
      "timestamp": 1762372169.4863174,
      "message": "测试失败",
      "error_details": "",
      "metadata": {}
    },
    "module_3_test_6": {
      "test_id": "module_3_test_6",
      "test_name": "测试用例 6",
      "module_name": "module_3",
      "status": "passed",
      "duration": 1.4804019586320196,
      "timestamp": 1762372169.5649352,
      "message": "测试执行完成",
      "error_details": "",
      "metadata": {}
    },
    "module_3_test_7": {
      "test_id": "module_3_test_7",
      "test_name": "测试用例 7",
      "module_name": "module_3",
      "status": "skipped",
      "duration": 0.10598483064909134,
      "timestamp": 1762372169.632088,
      "message": "测试失败",
      "error_details": "",
      "metadata": {}
    },
    "module_3_test_8": {
      "test_id": "module_3_test_8",
      "test_name": "测试用例 8",
      "module_name": "module_3",
      "status": "skipped",
      "duration": 2.2409305811557947,
      "timestamp": 1762372169.7037141,
      "message": "测试失败",
      "error_details": "",
      "metadata": {}
    },
    "module_3_test_9": {
      "test_id": "module_3_test_9",
      "test_name": "测试用例 9",
      "module_name": "module_3",
      "status": "passed",
      "duration": 0.40663749735947285,
      "timestamp": 1762372169.7719736,
      "message": "测试执行完成",
      "error_details": "",
      "metadata": {}
    },
    "module_3_test_10": {
      "test_id": "module_3_test_10",
      "test_name": "测试用例 10",
      "module_name": "module_3",
      "status": "passed",
      "duration": 2.831207268181005,
      "timestamp": 1762372169.8372068,
      "message": "测试执行完成",
      "error_details": "",
      "metadata": {}
    },
    "module_3_test_11": {
      "test_id": "module_3_test_11",
      "test_name": "测试用例 11",
      "module_name": "module_3",
      "status": "failed",
      "duration": 2.957220377465676,
      "timestamp": 1762372169.9105003,
      "message": "测试失败",
      "error_details": "",
      "metadata": {}
    },
    "module_3_test_12": {
      "test_id": "module_3_test_12",
      "test_name": "测试用例 12",
      "module_name": "module_3",
      "status": "failed",
      "duration": 1.4955823299348667,
      "timestamp": 1762372170.0346212,
      "message": "测试失败",
      "error_details": "",
      "metadata": {}
    },
    "module_3_test_13": {
      "test_id": "module_3_test_13",
      "test_name": "测试用例 13",
      "module_name": "module_3",
      "status": "failed",
      "duration": 4.116501796972617,
      "timestamp": 1762372170.1660073,
      "message": "测试失败",
      "error_details": "",
      "metadata": {}
    },
    "module_3_test_14": {
      "test_id": "module_3_test_14",
      "test_name": "测试用例 14",
      "module_name": "module_3",
      "status": "skipped",
      "duration": 4.868331682542096,
      "timestamp": 1762372170.307793,
      "message": "测试失败",
      "error_details": "",
      "metadata": {}
    },
    "module_3_test_15": {
      "test_id": "module_3_test_15",
      "test_name": "测试用例 15",
      "module_name": "module_3",
      "status": "skipped",
      "duration": 2.3044334799792745,
      "timestamp": 1762372170.3655672,
      "message": "测试失败",
      "error_details": "",
      "metadata": {}
    }
  }
}